ciso_assistant_client/__init__.py
ciso_assistant_client/client.py
ciso_assistant_client/exceptions.py
ciso_assistant_client/py.typed
ciso_assistant_client/models/__init__.py
ciso_assistant_client/models/assets.py
ciso_assistant_client/models/base.py
ciso_assistant_client/models/evidences.py
ciso_assistant_client/models/folders.py
ciso_aac-0.1.2.dist-info/METADATA
ciso_aac-0.1.2.dist-info/WHEEL
ciso_aac-0.1.2.dist-info/licenses/LICENSE
ciso_aac-0.1.2.dist-info/RECORD
