Metadata-Version: 2.4
Name: ciso-aac
Version: 0.1.2
Summary: A client library for accessing CISO Assistant API
Author-email: Johan Lundberg <lundberg@sunet.se>
License-Expression: BSD-2-Clause
License-File: LICENSE
Keywords: api,async,ciso-assistant,client,http,httpx,pydantic,rest
Classifier: Intended Audience :: Developers
Classifier: Operating System :: OS Independent
Classifier: Programming Language :: Python :: 3
Classifier: Programming Language :: Python :: 3 :: Only
Classifier: Programming Language :: Python :: 3.11
Classifier: Programming Language :: Python :: 3.12
Classifier: Programming Language :: Python :: 3.13
Classifier: Topic :: Internet :: WWW/HTTP
Classifier: Topic :: Software Development :: Libraries :: Python Modules
Classifier: Typing :: Typed
Requires-Python: >=3.11
Requires-Dist: httpx>=0.28.1
Requires-Dist: pydantic>=2.12.1
